textexploration/__init__.py
textexploration/broker/__init__.py
textexploration/broker/broker.py
textexploration/broker/request/__init__.py
textexploration/broker/request/condition.py
textexploration/broker/request/documents.py
textexploration/broker/request/request.py
textexploration/broker/response/__init__.py
textexploration/broker/response/response.py
textexploration-0.2.1.dist-info/LICENSE.txt
textexploration-0.2.1.dist-info/METADATA
textexploration-0.2.1.dist-info/WHEEL
textexploration-0.2.1.dist-info/top_level.txt
textexploration-0.2.1.dist-info/RECORD
