Metadata-Version: 2.1
Name: textexploration
Version: 0.2.1
Summary: UNKNOWN
Home-page: https://github.com/textexploration/python
Author: Matthijs Brouwer
Author-email: UNKNOWN
License: Apache License 2.0
Platform: UNKNOWN
Classifier: Framework :: Jupyter
Classifier: Intended Audience :: Developers
Classifier: Intended Audience :: Science/Research
Requires-Dist: requests (>=2.21.0)
Requires-Dist: pandas
